copyheaders/__init__.py
copyheaders/__version__.py
copyheaders/copyheaders.py
copyheaders-0.0.2.dist-info/LICENSE
copyheaders-0.0.2.dist-info/METADATA
copyheaders-0.0.2.dist-info/WHEEL
copyheaders-0.0.2.dist-info/top_level.txt
copyheaders-0.0.2.dist-info/RECORD
